telomere_airflow_provider-0.0.1.dist-info/licenses/LICENSE
telomere_provider/__init__.py
telomere_provider/provider.yaml
telomere_provider/hooks/__init__.py
telomere_provider/hooks/telomere.py
telomere_provider/operators/__init__.py
telomere_provider/operators/dag.py
telomere_provider/operators/telomere.py
telomere_provider/utils/__init__.py
telomere_provider/utils/dag_tracker.py
telomere_airflow_provider-0.0.1.dist-info/METADATA
telomere_airflow_provider-0.0.1.dist-info/WHEEL
telomere_airflow_provider-0.0.1.dist-info/entry_points.txt
telomere_airflow_provider-0.0.1.dist-info/top_level.txt
telomere_airflow_provider-0.0.1.dist-info/RECORD
