Metadata-Version: 2.4
Name: telomere-airflow-provider
Version: 0.0.1
Summary: Apache Airflow provider for Telomere lifecycle tracking
Author-email: Module Collective LLC <hello@modulecollective.com>
License: Apache-2.0
Project-URL: Homepage, https://github.com/modulecollective/telomere-airflow-provider
Project-URL: Documentation, https://github.com/modulecollective/telomere-airflow-provider#readme
Project-URL: Repository, https://github.com/modulecollective/telomere-airflow-provider
Project-URL: Bug Tracker, https://github.com/modulecollective/telomere-airflow-provider/issues
Classifier: Development Status :: 5 - Production/Stable
Classifier: Framework :: Apache Airflow
Classifier: Framework :: Apache Airflow :: Provider
Classifier: Intended Audience :: Developers
Classifier: License :: OSI Approved :: Apache Software License
Classifier: Programming Language :: Python :: 3
Classifier: Programming Language :: Python :: 3.8
Classifier: Programming Language :: Python :: 3.9
Classifier: Programming Language :: Python :: 3.10
Classifier: Programming Language :: Python :: 3.11
Classifier: Programming Language :: Python :: 3.12
Requires-Python: >=3.8
License-File: LICENSE
Requires-Dist: apache-airflow<3.0.0,>=2.5.0
Requires-Dist: requests>=2.28.0
Dynamic: license-file
